mullvad_python/__init__.py
mullvad_python/api.py
mullvad_python/banner.py
mullvad_python/cli.py
mullvad_python/dns_leak.py
mullvad_python-0.3.1.dist-info/entry_points.txt
mullvad_python-0.3.1.dist-info/LICENSE.md
mullvad_python-0.3.1.dist-info/WHEEL
mullvad_python-0.3.1.dist-info/METADATA
mullvad_python-0.3.1.dist-info/RECORD
